{
  "name": "train_10744_l_1.nii.gz",
  "protocol": "protocol2",
  "shape": [
    512,
    512,
    263
  ],
  "classified_findings": {
    "0": {
      "text": "Minimal emphysematous changes in both lungs",
      "category": "Others"
    },
    "1": {
      "text": "Linear atelectasis in both lungs",
      "category": "Atelectasis"
    },
    "2": {
      "text": "Several subcentimeter nonspecific nodules in both lungs",
      "category": "Lung Nodule"
    }
  },
  "categories": {
    "0": "1c",
    "1": "2a",
    "2": "2d"
  },
  "pixels": {
    "0": 2798,
    "1": 3594,
    "2": 109
  },
  "embedding_norm": 17.016271591186523,
  "mask_active_voxels": 68943872
}