{
  "name": "train_2867_a_2.nii.gz",
  "protocol": "protocol1",
  "shape": [
    512,
    512,
    494
  ],
  "classified_findings": {
    "0": {
      "text": "Pleuroparenchymal scarring changes in both lung apices",
      "category": "Others"
    },
    "1": {
      "text": "Minimal peribronchial thickening in both lungs",
      "category": "Others"
    },
    "2": {
      "text": "Several subcentimeter nonspecific nodules in both lungs",
      "category": "Lung Nodule"
    }
  },
  "categories": {
    "0": "2a",
    "1": "1a",
    "2": "2d"
  },
  "pixels": {
    "0": 1680,
    "1": 59755,
    "2": 1380
  },
  "embedding_norm": 17.572145462036133,
  "mask_active_voxels": 129499136
}