{
  "name": "train_8142_a_2.nii.gz",
  "protocol": "protocol2",
  "shape": [
    512,
    512,
    263
  ],
  "classified_findings": {
    "0": {
      "text": "Emphysematous changes in both lungs",
      "category": "Others"
    },
    "1": {
      "text": "Linear atelectasis in the right middle lobe",
      "category": "Atelectasis"
    },
    "2": {
      "text": "Linear atelectasis in the left upper lobe lingular segment",
      "category": "Atelectasis"
    },
    "3": {
      "text": "Linear atelectasis in the left lower lobe basal segments",
      "category": "Atelectasis"
    },
    "4": {
      "text": "Subcentimeter nodules in both lungs",
      "category": "Lung Nodule"
    }
  },
  "categories": {
    "0": "1c",
    "1": "2a",
    "2": "2a",
    "3": "2a",
    "4": "2d"
  },
  "pixels": {
    "0": 125,
    "1": 2584,
    "2": 1138,
    "3": 4051,
    "4": 117
  },
  "embedding_norm": 17.01637077331543,
  "mask_active_voxels": 68943872
}