{
  "name": "train_5254_b_1.nii.gz",
  "protocol": "protocol2",
  "shape": [
    512,
    512,
    324
  ],
  "classified_findings": {
    "0": {
      "text": "Reticulonodular fibrotic density increases in both lung apices",
      "category": "Others"
    },
    "1": {
      "text": "Focal ground glass opacities in the subpleural area of the right lower lobe basal segments",
      "category": "Lung opacity"
    }
  },
  "categories": {
    "0": "1d",
    "1": "2c"
  },
  "pixels": {
    "0": 254977,
    "1": 6776
  },
  "embedding_norm": 17.16112518310547,
  "mask_active_voxels": 84934656
}