{
  "name": "train_6829_a_2.nii.gz",
  "protocol": "protocol2",
  "shape": [
    512,
    512,
    456
  ],
  "classified_findings": {
    "0": {
      "text": "Sequelae calcific nodules, more prominent in the right lung",
      "category": "Lung Nodule"
    },
    "1": {
      "text": "Pleuroparenchymal band formations extending to the pleura",
      "category": "Others"
    },
    "2": {
      "text": "Bronchiectatic changes in the lower lobes of both lungs",
      "category": "Others"
    }
  },
  "categories": {
    "0": "2d",
    "1": "2a",
    "2": "1b"
  },
  "pixels": {
    "0": 1047,
    "1": 9257,
    "2": 1728
  },
  "embedding_norm": 17.440279006958008,
  "mask_active_voxels": 119537664
}