{
  "name": "train_7116_a_2.nii.gz",
  "protocol": "protocol2",
  "shape": [
    512,
    512,
    430
  ],
  "classified_findings": {
    "0": {
      "text": "Patchy ground-glass opacities in the upper lobes of both lungs",
      "category": "Lung opacity"
    },
    "1": {
      "text": "Patchy ground-glass opacities in the middle lobe of the right lung",
      "category": "Lung opacity"
    }
  },
  "categories": {
    "0": "2c",
    "1": "2c"
  },
  "pixels": {
    "0": 7271,
    "1": 1862
  },
  "embedding_norm": 17.501178741455078,
  "mask_active_voxels": 112721920
}