{
  "name": "train_6133_a_1.nii.gz",
  "protocol": "protocol2",
  "shape": [
    512,
    512,
    335
  ],
  "classified_findings": {
    "0": {
      "text": "Nodules and nodular consolidations with surrounding ground glass opacities (Halo sign) in the lower lobe of both lungs, the middle lobe, and the upper lobe of the right lung, more prominently on the right",
      "category": "Lung Nodule"
    }
  },
  "categories": {
    "0": "2b"
  },
  "pixels": {
    "0": 5406
  },
  "embedding_norm": 17.34381866455078,
  "mask_active_voxels": 87818240
}