{
  "name": "train_346_a_1.nii.gz",
  "protocol": "protocol1",
  "shape": [
    512,
    512,
    273
  ],
  "classified_findings": {
    "0": {
      "text": "Cystic bronchiectasis in the peripheral regions of the lower lobes bilaterally",
      "category": "Others"
    },
    "1": {
      "text": "Peribronchial thickening in both lungs, more pronounced in the lower lobes",
      "category": "Others"
    },
    "2": {
      "text": "Minimal ground-glass opacities in both lungs",
      "category": "Lung opacity"
    },
    "3": {
      "text": "Tree-in-bud patterns in both lungs",
      "category": "Others"
    },
    "4": {
      "text": "Indeterminate subcentimeter nodules in the left lung",
      "category": "Lung Nodule"
    }
  },
  "categories": {
    "0": "1b",
    "1": "1a",
    "2": "2c",
    "3": "1e",
    "4": "2d"
  },
  "pixels": {
    "0": 184624,
    "1": 62202,
    "2": 42481,
    "3": 546754,
    "4": 1784
  },
  "embedding_norm": 17.031326293945312,
  "mask_active_voxels": 71565312
}