{
  "name": "train_7597_a_2.nii.gz",
  "protocol": "protocol2",
  "shape": [
    512,
    512,
    274
  ],
  "classified_findings": {
    "0": {
      "text": "2 mm diameter nodule in the anterior segment of the left upper lobe",
      "category": "Lung Nodule"
    },
    "1": {
      "text": "Linear areas of atelectasis in the upper lobe of both lungs",
      "category": "Atelectasis"
    },
    "2": {
      "text": "Linear areas of atelectasis in the lateral segment of the right middle lobe",
      "category": "Atelectasis"
    },
    "3": {
      "text": "Linear areas of atelectasis in the lingular segment of the left upper lobe",
      "category": "Atelectasis"
    },
    "4": {
      "text": "Linear areas of atelectasis in the medial segment of the left lower lobe",
      "category": "Atelectasis"
    },
    "5": {
      "text": "Subcentimeter parenchymal air cyst in the superior segment of the right lower lobe",
      "category": "Others"
    }
  },
  "categories": {
    "0": "2d",
    "1": "2a",
    "2": "2a",
    "3": "2a",
    "4": "2a",
    "5": "2d"
  },
  "pixels": {
    "0": 138,
    "1": 376,
    "2": 1110,
    "3": 2288,
    "4": 879,
    "5": 215
  },
  "embedding_norm": 17.03125762939453,
  "mask_active_voxels": 71827456
}