{
  "name": "train_2813_a_1.nii.gz",
  "protocol": "protocol1",
  "shape": [
    512,
    512,
    373
  ],
  "classified_findings": {
    "0": {
      "text": "Fibrotic changes in the apices of both upper lobes",
      "category": "Others"
    },
    "1": {
      "text": "6 mm subpleural nodule in the lateral segment of the right middle lobe",
      "category": "Lung Nodule"
    },
    "2": {
      "text": "Minimal fibrotic densities adjacent to the 6 mm subpleural nodule in the lateral segment of the right middle lobe",
      "category": "Lung Nodule"
    }
  },
  "categories": {
    "0": "2a",
    "1": "2d",
    "2": "2a"
  },
  "pixels": {
    "0": 6668,
    "1": 1351,
    "2": 658
  },
  "embedding_norm": 17.30341148376465,
  "mask_active_voxels": 97779712
}