{
  "name": "train_12179_a_2.nii.gz",
  "protocol": "protocol2",
  "shape": [
    512,
    512,
    473
  ],
  "classified_findings": {
    "0": {
      "text": "Ground glass opacities in the superior segment of the left lower lobe",
      "category": "Lung opacity"
    },
    "1": {
      "text": "Crazy paving appearance in the superior segment of the left lower lobe",
      "category": "Others"
    }
  },
  "categories": {
    "0": "2c",
    "1": "2c"
  },
  "pixels": {
    "0": 85452,
    "1": 85452
  },
  "embedding_norm": 17.593708038330078,
  "mask_active_voxels": 123994112
}