{
  "name": "train_7569_d_2.nii.gz",
  "protocol": "protocol2",
  "shape": [
    512,
    512,
    444
  ],
  "classified_findings": {
    "0": {
      "text": "Minimal bronchiectasis in both lungs, predominantly in the central regions",
      "category": "Others"
    },
    "1": {
      "text": "Emphysematous changes in both lungs",
      "category": "Others"
    },
    "2": {
      "text": "Honeycomb appearance most prominent in the peripheral areas of both lungs",
      "category": "Others"
    },
    "3": {
      "text": "Central and peripheral consolidations, particularly in the upper lobe of the left lung",
      "category": "Consolidation"
    },
    "4": {
      "text": "Consolidation in the posterobasal segment of the right lower lobe",
      "category": "Consolidation"
    }
  },
  "categories": {
    "0": "1b",
    "1": "1c",
    "2": "2f",
    "3": "2b",
    "4": "2b"
  },
  "pixels": {
    "0": 9934,
    "1": 26471,
    "2": 100632,
    "3": 51942,
    "4": 128640
  },
  "embedding_norm": 17.526159286499023,
  "mask_active_voxels": 116391936
}