{
  "name": "train_11487_a_2.nii.gz",
  "protocol": "protocol2",
  "shape": [
    512,
    512,
    247
  ],
  "classified_findings": {
    "0": {
      "text": "Atelectasis in the lingular segment of the left upper lobe",
      "category": "Atelectasis"
    },
    "1": {
      "text": "Atelectasis in the left lower lobe",
      "category": "Atelectasis"
    }
  },
  "categories": {
    "0": "2b",
    "1": "2b"
  },
  "pixels": {
    "0": 485,
    "1": 1363
  },
  "embedding_norm": 16.953584671020508,
  "mask_active_voxels": 64749568
}